dunner/__init__.py
dunner/data_cleaner.py
dunner/data_operations.py
dunner/preprocess_helper.py
Dunner-0.0.1.6.dist-info/LICENSE
Dunner-0.0.1.6.dist-info/METADATA
Dunner-0.0.1.6.dist-info/WHEEL
Dunner-0.0.1.6.dist-info/top_level.txt
Dunner-0.0.1.6.dist-info/RECORD
