Metadata-Version: 2.1
Name: Dunner
Version: 0.0.1.6
Summary: A helper package for data science projects
Home-page: https://github.com/ebegen/Dunner
Author: Emre Begen
Author-email: ebegen51@gmail.com
License: UNKNOWN
Platform: UNKNOWN
Classifier: Development Status :: 2 - Pre-Alpha
Classifier: Programming Language :: Python
Classifier: Programming Language :: Python :: 3.5
Classifier: Programming Language :: Python :: 3.6
Classifier: Programming Language :: Python :: 3.7
Classifier: License :: OSI Approved :: MIT License
Classifier: Operating System :: OS Independent
Requires-Dist: numpy
Requires-Dist: pandas
Requires-Dist: scikit-learn
Requires-Dist: swifter
Requires-Dist: feather-format
Requires-Dist: dask
